historicalFinancialData/__init__.py
historicalFinancialData/exceptions.py
historicalFinancialData/main.py
historicalFinancialData/utils.py
historicalFinancialData-0.1.3.dist-info/LICENSE.md
historicalFinancialData-0.1.3.dist-info/METADATA
historicalFinancialData-0.1.3.dist-info/WHEEL
historicalFinancialData-0.1.3.dist-info/top_level.txt
historicalFinancialData-0.1.3.dist-info/RECORD
