Metadata-Version: 2.1
Name: historicalFinancialData
Version: 0.1.3
Summary: A package for public companies' historical financial data
Home-page: https://github.com/DanielMistrik/HistoricFinancialData
Author: Daniel Mistrik
Author-email: danielkomist@gmail.com
License: Apache 2.0 License
Classifier: Development Status :: 3 - Alpha
Classifier: Intended Audience :: Developers
Classifier: Programming Language :: Python :: 3.10
Classifier: License :: OSI Approved :: Apache Software License
Classifier: Operating System :: OS Independent
License-File: LICENSE.md
Requires-Dist: ratelimit
Requires-Dist: numpy
Requires-Dist: requests
Requires-Dist: pypandoc
